pygraphml/__init__.py
pygraphml/attribute.py
pygraphml/edge.py
pygraphml/graph.py
pygraphml/graphml_parser.py
pygraphml/item.py
pygraphml/node.py
pygraphml/point.py
pygraphml-2.2.dist-info/DESCRIPTION.rst
pygraphml-2.2.dist-info/METADATA
pygraphml-2.2.dist-info/RECORD
pygraphml-2.2.dist-info/WHEEL
pygraphml-2.2.dist-info/metadata.json
pygraphml-2.2.dist-info/top_level.txt
