Metadata-Version: 1.1
Name: pygraphml
Version: 2.2
Summary: Small library to parse GraphML files in Python
Home-page: https://github.com/hadim/pygraphml/
Author: Hadrien Mary
Author-email: hadrien.mary@gmail.com
License: UNKNOWN
Platform: UNKNOWN
Classifier: Development Status :: 5 - Production/Stable
Classifier: Intended Audience :: Developers
Classifier: Natural Language :: English
Classifier: License :: OSI Approved :: BSD License
Classifier: Operating System :: OS Independent
Classifier: Programming Language :: Python
Classifier: Programming Language :: Python :: 2
Classifier: Programming Language :: Python :: 2.7
Classifier: Programming Language :: Python :: 3
Classifier: Programming Language :: Python :: 3.4
